MANIFEST.in
README.md
setup.py
pywhdfs/__init__.py
pywhdfs/client.py
pywhdfs/cmdtool.py
pywhdfs/config.py
pywhdfs.egg-info/PKG-INFO
pywhdfs.egg-info/SOURCES.txt
pywhdfs.egg-info/dependency_links.txt
pywhdfs.egg-info/entry_points.txt
pywhdfs.egg-info/requires.txt
pywhdfs.egg-info/top_level.txt
pywhdfs/resources/__init__.py
pywhdfs/resources/config_schema.json
pywhdfs/utils/__init__.py
pywhdfs/utils/crc32c.py
pywhdfs/utils/hglob.py
pywhdfs/utils/utils.py